encryption3/nonlinear_encryption_module3.v
// nonlinear_encryption_module.v
module nonlinear_encryption_module3 #(parameter N = 8) (
    input wire [N-1:0] data_in,
    input wire [N-1:0] key,
    output reg [N-1:0] data_out
);
    integer i;
    reg [N-1:0] intermediate;

    always @(*) begin
        // First stage: XOR with key and rotate
        for (i = 0; i < N; i = i + 1) begin
            intermediate[i] = data_in[i] ^ key[i];
        end

        // Second stage: Nonlinear transformation
        for (i = 0; i < N; i = i + 1) begin
            data_out[i] = (intermediate[i] + (intermediate[(i+1) % N] & key[i])) % 2;
        end
    end
endmodule

encryption3/tb_nonlinear_encryption_module.v
// tb_nonlinear_encryption_module.v
`timescale 1ns / 1ps

module tb_nonlinear_encryption_module;

parameter N = 8;
reg [N-1:0] data_in;
reg [N-1:0] key;
wire [N-1:0] data_out;
reg [N-1:0] expected_data_out;

nonlinear_encryption_module3 #(N) uut (
    .data_in(data_in),
    .key(key),
    .data_out(data_out)
);

function [N-1:0] calculate_expected_output;
    input [N-1:0] data;
    input [N-1:0] k;
    integer i;
    reg [N-1:0] intermediate;
    begin
        for (i = 0; i < N; i = i + 1) begin
            intermediate[i] = data[i] ^ k[i];
        end
        for (i = 0; i < N; i = i + 1) begin
            calculate_expected_output[i] = (intermediate[i] + (intermediate[(i+1) % N] & k[i])) % 2;
        end
    end
endfunction

initial begin
    $dumpfile("nonlinear_waveform.vcd");
    $dumpvars(0, tb_nonlinear_encryption_module);

    // Test Vector 1
    data_in = 8'b10101010; 
    key = 8'b11111111; 
    expected_data_out = calculate_expected_output(data_in, key);    
    #10; 
    perform_test();

    // Test Vector 2
    data_in = 8'b01010101; 
    key = 8'b00000000; 
    expected_data_out = calculate_expected_output(data_in, key);    
    #10; 
    perform_test();

    // Test Vector 3
    data_in = 8'b00000000; 
    key = 8'b10101010; 
    expected_data_out = calculate_expected_output(data_in, key);    
    #10; 
    perform_test();

    // Test Vector 4
    data_in = 8'b11111111; 
    key = 8'b01010101; 
    expected_data_out = calculate_expected_output(data_in, key);    
    #10; 
    perform_test();

    // Test Vector 5
    data_in = 8'b00011011; 
    key = 8'b10101010; 
    expected_data_out = calculate_expected_output(data_in, key);    
    #10; 
    perform_test();

    // Test Vector 6
    data_in = 8'b10010110; 
    key = 8'b01100101; 
    expected_data_out = calculate_expected_output(data_in, key);    
    #10; 
    perform_test();

    // Test Vector 7
    data_in = 8'b00000001; 
    key = 8'b01010101; 
    expected_data_out = calculate_expected_output(data_in, key);    
    #10; 
    perform_test();

    // Test Vector 8
    data_in = 8'b00000010; 
    key = 8'b01010101; 
    expected_data_out = calculate_expected_output(data_in, key);    
    #10; 
    perform_test();

    $display("All tests passed.");
    $finish;
end

task perform_test;
    begin
        $display("Time: %t, Input: %b, Key: %b, Output: %b, Expected: %b", 
                 $time, data_in, key, data_out, expected_data_out);
        if (data_out !== expected_data_out) begin
            $display("Error: Output does not match expected value.");
            $finish;
        end
    end
endtask

endmodule

encryption3/nonlinear_waveform.vcd
$date
	Sun Dec 10 15:58:41 2023
$end
$version
	Icarus Verilog
$end
$timescale
	1ps
$end
$scope module tb_nonlinear_encryption_module $end
$var wire 8 ! data_out [7:0] $end
$var parameter 32 " N $end
$var reg 8 # data_in [7:0] $end
$var reg 8 $ expected_data_out [7:0] $end
$var reg 8 % key [7:0] $end
$scope function calculate_expected_output $end
$var reg 8 & data [7:0] $end
$var reg 8 ' intermediate [7:0] $end
$var reg 8 ( k [7:0] $end
$var integer 32 ) i [31:0] $end
$upscope $end
$scope module uut $end
$var wire 8 * data_in [7:0] $end
$var wire 8 + key [7:0] $end
$var parameter 32 , N $end
$var reg 8 - data_out [7:0] $end
$var reg 8 . intermediate [7:0] $end
$var integer 32 / i [31:0] $end
$upscope $end
$scope task perform_test $end
$upscope $end
$upscope $end
$enddefinitions $end
$comment Show the parameter values. $end
$dumpall
b1000 ,
b1000 "
$end
#0
$dumpvars
b1000 /
b1010101 .
b11111111 -
b11111111 +
b10101010 *
b1000 )
b11111111 (
b1010101 '
b10101010 &
b11111111 %
b11111111 $
b10101010 #
b11111111 !
$end
#10000
b1010101 !
b1010101 -
b1000 /
b1010101 $
b1000 )
b1010101 &
b0 (
b0 %
b0 +
b1010101 #
b1010101 *
#20000
b10101010 !
b10101010 -
b10101010 .
b1000 /
b10101010 $
b10101010 '
b1000 )
b0 &
b10101010 (
b10101010 %
b10101010 +
b0 #
b0 *
#30000
b11111111 !
b11111111 -
b1000 /
b11111111 $
b1000 )
b11111111 &
b1010101 (
b1010101 %
b1010101 +
b11111111 #
b11111111 *
#40000
b111001 !
b111001 -
b10110001 .
b1000 /
b111001 $
b10110001 '
b1000 )
b11011 &
b10101010 (
b10101010 %
b10101010 +
b11011 #
b11011 *
#50000
b10010010 !
b10010010 -
b11110011 .
b1000 /
b10010010 $
b11110011 '
b1000 )
b10010110 &
b1100101 (
b1100101 %
b1100101 +
b10010110 #
b10010110 *
#60000
b1010100 !
b1010100 -
b1010100 .
b1000 /
b1010100 $
b1010100 '
b1000 )
b1 &
b1010101 (
b1010101 %
b1010101 +
b1 #
b1 *
#70000
b1010110 !
b1010110 -
b1010111 .
b1000 /
b1010110 $
b1010111 '
b1000 )
b10 &
b10 #
b10 *
